odoo/addons/maintenance_equipment_status/README.rst
odoo/addons/maintenance_equipment_status/__init__.py
odoo/addons/maintenance_equipment_status/__manifest__.py
odoo/addons/maintenance_equipment_status/data/demo_maintenance_equipment_status.xml
odoo/addons/maintenance_equipment_status/i18n/es.po
odoo/addons/maintenance_equipment_status/i18n/it.po
odoo/addons/maintenance_equipment_status/i18n/maintenance_equipment_status.pot
odoo/addons/maintenance_equipment_status/models/__init__.py
odoo/addons/maintenance_equipment_status/models/maintenance_equipment.py
odoo/addons/maintenance_equipment_status/models/maintenance_equipment_status.py
odoo/addons/maintenance_equipment_status/readme/CONFIGURATION.rst
odoo/addons/maintenance_equipment_status/readme/CONTRIBUTORS.md
odoo/addons/maintenance_equipment_status/readme/DESCRIPTION.md
odoo/addons/maintenance_equipment_status/security/ir.model.access.csv
odoo/addons/maintenance_equipment_status/static/description/icon.png
odoo/addons/maintenance_equipment_status/static/description/index.html
odoo/addons/maintenance_equipment_status/views/maintenance_equipment_status_views.xml
odoo/addons/maintenance_equipment_status/views/maintenance_equipment_views.xml
odoo_addon_maintenance_equipment_status-17.0.1.0.0.3.dist-info/METADATA
odoo_addon_maintenance_equipment_status-17.0.1.0.0.3.dist-info/WHEEL
odoo_addon_maintenance_equipment_status-17.0.1.0.0.3.dist-info/top_level.txt
odoo_addon_maintenance_equipment_status-17.0.1.0.0.3.dist-info/RECORD
