Metadata-Version: 2.1
Name: odoo-addon-maintenance_equipment_status
Version: 17.0.1.0.0.3
Requires-Python: >=3.10
Requires-Dist: odoo-addon-base_maintenance>=17.0dev,<17.1dev
Requires-Dist: odoo>=17.0a,<17.1dev
Summary: Maintenance Equipment Status
Home-page: https://github.com/OCA/maintenance
License: LGPL-3
Author: ForgeFlow, Odoo Community Association (OCA)
Author-email: support@odoo-community.org
Classifier: Programming Language :: Python
Classifier: Framework :: Odoo
Classifier: Framework :: Odoo :: 17.0
Classifier: License :: OSI Approved :: GNU Lesser General Public License v3 (LGPLv3)
